surface_reconstruction/__init__.py
surface_reconstruction/open3d_surface.py
surface_reconstruction/pymeshlab_surface.py
surface_reconstruction/singleton_meta.py
surface_reconstruction/surface_reconstruction.py
surface_reconstruction/surface_strategy.py
surface_reconstruction/version.py
surface_reconstruction/batch_visualization/open3d_batch.py
surface_reconstruction/batch_visualization/open3d_batch_structured.py
surface_reconstruction/batch_visualization/pymeshlab_batch.py
surface_reconstruction-0.1.3.data/data/data/filter_script.mlx
surface_reconstruction-0.1.3.data/data/data/list_vertex.ply
surface_reconstruction-0.1.3.dist-info/METADATA
surface_reconstruction-0.1.3.dist-info/WHEEL
surface_reconstruction-0.1.3.dist-info/top_level.txt
surface_reconstruction-0.1.3.dist-info/RECORD
