Metadata-Version: 2.1
Name: surface-reconstruction
Version: 0.1.3
Summary: Import a point cloud file and perform poisson 3D surface reconstruction algorithm, integrated with third-party libraries (e.g. open3d, pymeshlab...)
Home-page: https://github.com/mfdeveloper/surface_reconstruction_python
Author: Felipe Michel Ferreira
Author-email: mfelipeof@gmail.com
License: MIT
Keywords: point-cloud,surface-reconstruction,3d-processor,3d-rendering,3D,poisson,open3d,meshlab
Platform: UNKNOWN
Classifier: License :: OSI Approved :: MIT License
Classifier: Operating System :: OS Independent
Classifier: Topic :: Multimedia :: Graphics :: 3D Rendering
Classifier: Environment :: GPU
Classifier: Development Status :: 5 - Production/Stable
Classifier: Programming Language :: Python :: 3
Classifier: Programming Language :: Python :: 3.8
Requires-Python: >=3.3
Requires-Dist: open3d (==0.12)
Requires-Dist: pymeshlab (==0.2)
Requires-Dist: numpy
